mkmr/__init__.py
mkmr/edmr.py
mkmr/instance.py
mkmr/mgmr.py
mkmr/mkmr.py
mkmr/utils.py
mkmr/vimr.py
mkmr-0.0.35.dist-info/entry_points.txt
mkmr-0.0.35.dist-info/WHEEL
mkmr-0.0.35.dist-info/METADATA
mkmr-0.0.35.dist-info/RECORD
