Metadata-Version: 2.1
Name: mkmr
Version: 0.0.35
Summary: Collection of tools for dealing with GitLab Merge Requests, with an Alpine flavour.
Home-page: https://gitlab.alpinelinux.org/Leo/mkmr
License: GPL-3.0-or-later
Author: Leo
Author-email: thinkabit.ukim@gmail.com
Requires-Python: >=3.7
Classifier: Topic :: Utilities
Classifier: Topic :: Software Development :: Version Control :: Git
Classifier: Intended Audience :: Other Audience
Classifier: License :: OSI Approved :: GNU General Public License v3 or later (GPLv3+)
Classifier: Development Status :: 2 - Pre-Alpha
Classifier: Programming Language :: Python :: 3
Classifier: Programming Language :: Python :: 3.8
Classifier: Programming Language :: Python :: 3.7
Classifier: Operating System :: POSIX
Requires-Dist: gitpython>=3.0.0,<4
Requires-Dist: python-gitlab>=2.0.0,<3
Requires-Dist: python-editor>=1.0.0,<2
Requires-Dist: inquirer>=2.6.0,<3
Requires-Dist: giturlparse>=0.9.0,<1
